[ { "case_id" : "5403030",
    "chp_road_type" : "0",
    "collision_date" : "20120119",
    "collision_severity" : "1",
    "collision_time" : "0545",
    "count_bicyclist_killed" : "0",
    "count_ped_killed" : "0",
    "direction" : "W",
    "distance" : "72",
    "hit_and_run" : "N",
    "long" : "-118.411732",
    "lat" : "34.020479",
    "mviw" : "-",
    "number_injured" : "0",
    "number_killed" : "1",
    "pcf_viol_category" : "22",
    "pcf_viol_subsection" : "",
    "pcf_violation" : "",
    "primary_rd" : "VANOWEN ST",
    "road_surface" : "A",
    "secondary_rd" : "BERQUIST AV",
    "type_of_collision" : "C",
    "weather_1" : "A"
  },
  { "case_id" : "5403038",
    "chp_road_type" : "0",
    "collision_date" : "20120105",
    "collision_severity" : "1",
    "collision_time" : "1145",
    "count_bicyclist_killed" : "0",
    "count_ped_killed" : "0",
    "direction" : "",
    "distance" : "0",
    "hit_and_run" : "N",
    "long" : "-90.1987043",
    "lat" : "34.5026059",
    "mviw" : "C",
    "number_injured" : "0",
    "number_killed" : "1",
    "pcf_viol_category" : "09",
    "pcf_viol_subsection" : "A",
    "pcf_violation" : "21802",
    "primary_rd" : "CRENSHAW BL",
    "road_surface" : "A",
    "secondary_rd" : "54TH ST",
    "type_of_collision" : "D",
    "weather_1" : "A"
  },
  { "case_id" : "5403042",
    "chp_road_type" : "0",
    "collision_date" : "20120103",
    "collision_severity" : "1",
    "collision_time" : "0045",
    "count_bicyclist_killed" : "0",
    "count_ped_killed" : "0",
    "direction" : "",
    "distance" : "0",
    "hit_and_run" : "N",
    "long" : "-114.1494117",
    "lat" : "34.8722245",
    "mviw" : "C",
    "number_injured" : "2",
    "number_killed" : "1",
    "pcf_viol_category" : "01",
    "pcf_viol_subsection" : "A",
    "pcf_violation" : "23152",
    "primary_rd" : "YUCCA ST",
    "road_surface" : "A",
    "secondary_rd" : "VINE ST",
    "type_of_collision" : "D",
    "weather_1" : "A"
  },
  { "case_id" : "5403084",
    "chp_road_type" : "0",
    "collision_date" : "20120118",
    "collision_severity" : "1",
    "collision_time" : "1405",
    "count_bicyclist_killed" : "0",
    "count_ped_killed" : "1",
    "direction" : "E",
    "distance" : "41",
    "hit_and_run" : "N",
    "long" : "-123.7585240",
    "lat" : "48.9452039",
    "mviw" : "B",
    "number_injured" : "0",
    "number_killed" : "1",
    "pcf_viol_category" : "11",
    "pcf_viol_subsection" : "A",
    "pcf_violation" : "21954",
    "primary_rd" : "SALTAIR TER",
    "road_surface" : "A",
    "secondary_rd" : "SALTAIR AV",
    "type_of_collision" : "G",
    "weather_1" : "A"
  },
  { "case_id" : "5403154",
    "chp_road_type" : "0",
    "collision_date" : "20120118",
    "collision_severity" : "1",
    "collision_time" : "1935",
    "count_bicyclist_killed" : "0",
    "count_ped_killed" : "0",
    "direction" : "E",
    "distance" : "355",
    "hit_and_run" : "N",
    "long" : "-2.2479260",
    "lat" : "53.4792510",
    "mviw" : "E",
    "number_injured" : "4",
    "number_killed" : "1",
    "pcf_viol_category" : "05",
    "pcf_viol_subsection" : "A",
    "pcf_violation" : "21651",
    "primary_rd" : "MANCHESTER AV",
    "road_surface" : "A",
    "secondary_rd" : "DENKER AV",
    "type_of_collision" : "A",
    "weather_1" : "A"
  }
]
